adaptRetriever/__init__.py
adaptRetriever/main.py
adaptRetriever-0.4.0.dist-info/METADATA
adaptRetriever-0.4.0.dist-info/WHEEL
adaptRetriever-0.4.0.dist-info/top_level.txt
adaptRetriever-0.4.0.dist-info/RECORD
