Metadata-Version: 2.1
Name: adaptRetriever
Version: 0.4.0
